odoo/addons/pos_partner_vat_valid/README.rst
odoo/addons/pos_partner_vat_valid/__init__.py
odoo/addons/pos_partner_vat_valid/__manifest__.py
odoo/addons/pos_partner_vat_valid/i18n/ca.po
odoo/addons/pos_partner_vat_valid/i18n/es.po
odoo/addons/pos_partner_vat_valid/i18n/it.po
odoo/addons/pos_partner_vat_valid/i18n/pos_partner_vat_valid.pot
odoo/addons/pos_partner_vat_valid/models/__init__.py
odoo/addons/pos_partner_vat_valid/models/res_partner.py
odoo/addons/pos_partner_vat_valid/readme/CONTRIBUTORS.md
odoo/addons/pos_partner_vat_valid/readme/DESCRIPTION.md
odoo/addons/pos_partner_vat_valid/static/description/icon.png
odoo/addons/pos_partner_vat_valid/static/description/icon.svg
odoo/addons/pos_partner_vat_valid/static/description/index.html
odoo/addons/pos_partner_vat_valid/static/src/app/PartnerDetailsEdit.esm.js
odoo/addons/pos_partner_vat_valid/tests/__init__.py
odoo/addons/pos_partner_vat_valid/tests/test_verify_vat.py
odoo_addon_pos_partner_vat_valid-17.0.1.0.0.4.dist-info/METADATA
odoo_addon_pos_partner_vat_valid-17.0.1.0.0.4.dist-info/WHEEL
odoo_addon_pos_partner_vat_valid-17.0.1.0.0.4.dist-info/top_level.txt
odoo_addon_pos_partner_vat_valid-17.0.1.0.0.4.dist-info/RECORD
